nonebot_plugin_ygo/__init__.py
nonebot_plugin_ygo/config.py
nonebot_plugin_ygo-1.0.2.dist-info/METADATA
nonebot_plugin_ygo-1.0.2.dist-info/WHEEL
nonebot_plugin_ygo-1.0.2.dist-info/top_level.txt
nonebot_plugin_ygo-1.0.2.dist-info/RECORD
