Metadata-Version: 2.1
Name: nonebot-plugin-ygo
Version: 1.0.2
Summary: nonebot的游戏王卡查插件
Home-page: https://github.com/anlen123/nonebot_plugin_ygo
Author: anlen123
Author-email: 1761512493@qq.com
Maintainer: anlen123
Maintainer-email: 1761512493@qq.com
License: UNKNOWN
Platform: all
Requires-Dist: aiohttp
Requires-Dist: nonebot-adapter-onebot (<3.0.0,>=2.0.0-beta.1)
Requires-Dist: nonebot2 (<3.0.0,>=2.0.0-beta.1)
